uhlive/__init__.py
uhlive/auth.py
uhlive/py.typed
uhlive/stream/__init__.py
uhlive/stream/conversation/__init__.py
uhlive/stream/conversation/client.py
uhlive/stream/conversation/error.py
uhlive/stream/conversation/events.py
uhlive/stream/conversation/human_datetime.py
uhlive/stream/recognition/__init__.py
uhlive/stream/recognition/client.py
uhlive/stream/recognition/events.py
uhlive-1.6.1.dist-info/LICENSE
uhlive-1.6.1.dist-info/METADATA
uhlive-1.6.1.dist-info/WHEEL
uhlive-1.6.1.dist-info/top_level.txt
uhlive-1.6.1.dist-info/RECORD
