Metadata-Version: 2.1
Name: uhlive
Version: 1.6.1
Summary: Python bindings for the Uh!ive APIs
Home-page: https://github.com/uhlive/python-sdk
Author: Allo-Media
Author-email: support@allo-media.fr
License: MIT
Classifier: Development Status :: 5 - Production/Stable
Classifier: Programming Language :: Python :: 3
Classifier: Programming Language :: Python :: 3.7
Classifier: Programming Language :: Python :: 3.8
Classifier: Programming Language :: Python :: 3.9
Classifier: Programming Language :: Python :: 3.10
Classifier: Programming Language :: Python :: 3.11
Classifier: Programming Language :: Python :: 3.12
Classifier: Programming Language :: Python :: 3.13
Classifier: Intended Audience :: Developers
Classifier: Operating System :: POSIX :: Linux
Classifier: Topic :: Software Development :: Libraries :: Python Modules
Requires-Python: >=3.7
License-File: LICENSE
Provides-Extra: examples
Requires-Dist: websocket-client; extra == "examples"
Requires-Dist: requests; extra == "examples"
Requires-Dist: aiohttp; extra == "examples"
Requires-Dist: sounddevice; extra == "examples"
Requires-Dist: toml; extra == "examples"
